fastapi_allauth/__init__.py
fastapi_allauth/allauth_manager.py
fastapi_allauth/secret_handler.py
fastapi_allauth/auth/__init__.py
fastapi_allauth/auth/authenticate.py
fastapi_allauth/auth/login.py
fastapi_allauth/auth/register.py
fastapi_allauth/model/BaseUser.py
fastapi_allauth/model/__init__.py
fastapi_allauth/oauth/BaseOauth.py
fastapi_allauth/oauth/DiscordOauth.py
fastapi_allauth/oauth/FacebookOauth.py
fastapi_allauth/oauth/GithubOauth.py
fastapi_allauth/oauth/GoogleOauth.py
fastapi_allauth/oauth/KakaoOauth.py
fastapi_allauth/oauth/NaverOauth.py
fastapi_allauth/oauth/__init__.py
fastapi_allauth-0.1.2.dist-info/LICENSE
fastapi_allauth-0.1.2.dist-info/METADATA
fastapi_allauth-0.1.2.dist-info/WHEEL
fastapi_allauth-0.1.2.dist-info/top_level.txt
fastapi_allauth-0.1.2.dist-info/RECORD
