Metadata-Version: 2.1
Name: fastapi-allauth
Version: 0.1.2
Summary: the simplest fastapi oauth package
Home-page: https://github.com/K-villain/fastapi-allauth
Author: villain
Author-email: sehwa98@icloud.com
Classifier: Programming Language :: Python :: 3
Classifier: License :: OSI Approved :: MIT License
Classifier: Operating System :: OS Independent
Requires-Python: >=3.7
License-File: LICENSE
Requires-Dist: fastapi (>=0.88.0)
Requires-Dist: pydantic (>=1.8.2)
Requires-Dist: starlette (>=0.14.2)
Requires-Dist: PyJWT (>=2.6.0)
